setup.py
src/__init__.py
src/zopyx/__init__.py
src/zopyx.slimp.egg-info/PKG-INFO
src/zopyx.slimp.egg-info/SOURCES.txt
src/zopyx.slimp.egg-info/dependency_links.txt
src/zopyx.slimp.egg-info/entry_points.txt
src/zopyx.slimp.egg-info/namespace_packages.txt
src/zopyx.slimp.egg-info/requires.txt
src/zopyx.slimp.egg-info/top_level.txt
src/zopyx.slimp.egg-info/zip-safe
src/zopyx/slimp/CHANGES.txt
src/zopyx/slimp/README.txt
src/zopyx/slimp/__init__.py
src/zopyx/slimp/slimp.py
src/zopyx/slimp/slimplayer.py
