Metadata-Version: 1.0
Name: zopyx.slimp
Version: 0.2.1
Summary: A Python interface for the slimserver software
Home-page: UNKNOWN
Author: Andreas Jung
Author-email: info@zopyx.com
License: ZPL (see LICENSE.txt)
Platform: UNKNOWN
Classifier: Programming Language :: Python
